frappe_mcp/__init__.py
frappe_mcp/cli/__init__.py
frappe_mcp/cli/utils.py
frappe_mcp/server/__init__.py
frappe_mcp/server/handlers.py
frappe_mcp/server/server.py
frappe_mcp/server/types.py
frappe_mcp/server/tests/__init__.py
frappe_mcp/server/tests/test_server.py
frappe_mcp/server/tests/test_tool_handlers.py
frappe_mcp/server/tools/__init__.py
frappe_mcp/server/tools/handlers.py
frappe_mcp/server/tools/test_tool_schema.py
frappe_mcp/server/tools/test_tools.py
frappe_mcp/server/tools/tool_schema.py
frappe_mcp-0.1.0.dist-info/METADATA
frappe_mcp-0.1.0.dist-info/WHEEL
frappe_mcp-0.1.0.dist-info/entry_points.txt
frappe_mcp-0.1.0.dist-info/licenses/LICENSE
frappe_mcp-0.1.0.dist-info/RECORD
