Metadata-Version: 2.4
Name: frappe-mcp
Version: 0.1.0
Summary: Frappe MCP allows building MCP compatibility into Frappe apps
Project-URL: Homepage, https://github.com/frappe/frappe-mcp
Project-URL: Documentation, https://github.com/frappe/frappe-mcp
Project-URL: Source, https://github.com/frappe/frappe-mcp
Author-email: Alan Tom <me@18alan.space>, Frappe Techonologies Pvt Ltd <developers@frappe.io>
License-Expression: MIT
License-File: LICENSE
Requires-Python: >=3.10
Requires-Dist: click~=8.2.0
Requires-Dist: jsonschema<5.0.0,>=4.24.0
Requires-Dist: pydantic~=2.11.7
Requires-Dist: werkzeug==3.1.3
